clevergui
