Metadata-Version: 2.1
Name: clevergui
Version: 0.0.1a2
Summary: Developer utilities and templates built around PySimpleGUI
Home-page: https://github.com/Pfython/clevergui
Author: Peter Fison
Author-email: peter@southwestlondon.tv
License: MIT License
Download-URL: https://github.com/Pfython/clevergui/archive/0.0.1a2.tar.gz
Keywords: clevergui,Pfython,Peter Fison
Platform: UNKNOWN
Classifier: Development Status :: 2 - Pre-Alpha
Classifier: Intended Audience :: Developers
Classifier: Operating System :: OS Independent
Classifier: Programming Language :: Python :: 3.6
Classifier: Programming Language :: Python :: 3.7
Classifier: Programming Language :: Python :: 3.8
Classifier: Programming Language :: Python :: 3.9
Classifier: Topic :: Software Development
Classifier: Topic :: Software Development :: Libraries :: Python Modules
Classifier: Topic :: Utilities
Classifier: License :: OSI Approved :: MIT License
